{
	"info": {
		"_postman_id": "c848e206-1d07-4a72-82aa-09a13dab168f",
		"name": "ChatBotApi",
		"schema": "https://schema.getpostman.com/json/collection/v2.1.0/collection.json",
		"_exporter_id": "26085550"
	},
	"item": [
		{
			"name": "http://127.0.0.1:5000/api/chat",
			"request": {
				"method": "POST",
				"header": [],
				"body": {
					"mode": "raw",
					"raw": "{\r\n  \"question\": \"What are the requisites of the course CIIC 4151?\"\r\n}",
					"options": {
						"raw": {
							"language": "json"
						}
					}
				},
				"url": {
					"raw": "http://127.0.0.1:5000/api/chat",
					"protocol": "http",
					"host": [
						"127",
						"0",
						"0",
						"1"
					],
					"port": "5000",
					"path": [
						"api",
						"chat"
					]
				}
			},
			"response": []
		},
		{
			"name": "http://127.0.0.1:5000/api/chat",
			"request": {
				"method": "POST",
				"header": [],
				"body": {
					"mode": "raw",
					"raw": "{\r\n  \"question\": \"How are grades divided in the INSO 5111 course? \"\r\n}",
					"options": {
						"raw": {
							"language": "json"
						}
					}
				},
				"url": {
					"raw": "http://127.0.0.1:5000/api/chat",
					"protocol": "http",
					"host": [
						"127",
						"0",
						"0",
						"1"
					],
					"port": "5000",
					"path": [
						"api",
						"chat"
					]
				}
			},
			"response": []
		},
		{
			"name": "http://127.0.0.1:5000/api/chat",
			"request": {
				"method": "POST",
				"header": [],
				"body": {
					"mode": "raw",
					"raw": "{\r\n  \"question\": \"What are the textbooks used in the Machine Learning course?\"\r\n}",
					"options": {
						"raw": {
							"language": "json"
						}
					}
				},
				"url": {
					"raw": "http://127.0.0.1:5000/api/chat",
					"protocol": "http",
					"host": [
						"127",
						"0",
						"0",
						"1"
					],
					"port": "5000",
					"path": [
						"api",
						"chat"
					]
				}
			},
			"response": []
		},
		{
			"name": "http://127.0.0.1:5000/api/chat",
			"request": {
				"method": "POST",
				"header": [],
				"body": {
					"mode": "raw",
					"raw": "{\r\n  \"question\": \"Tell me at least 3 topics that are taught in the introduction to database (CIIC4060) course?\"\r\n}",
					"options": {
						"raw": {
							"language": "json"
						}
					}
				},
				"url": {
					"raw": "http://127.0.0.1:5000/api/chat",
					"protocol": "http",
					"host": [
						"127",
						"0",
						"0",
						"1"
					],
					"port": "5000",
					"path": [
						"api",
						"chat"
					]
				}
			},
			"response": []
		}
	]
}